{
    "test-config" : "1",
    "local" : {
        "ip"    : "172.17.0.25",
        "gwip"  : "172.17.0.1",
        "ac-ip" : "10.17.1.25",
        "as"    : "1"
    },
    "remote" : {
        "ip"    : "172.17.0.23",
        "ac-ip" : "10.17.1.23",
        "as"    : "1"
    },
    "eth-if-index" : "0x71010001",
    "lif-if-index" : "0x7",
    "vni"          : "100",
    "route"        : {
        "dest_ip"  : "100.100.100.0",
        "nh_ip"    : "172.17.0.1",
        "prefix"   : "24"
    },
    "manual-rd"      : "0",
    "manual-rt"      : "0",
    "route-target"        : ["0","2","0","1","16","0","0","100"],
    "route-distinguisher" : ["0","1","172","17","0","25","0","1"]
}
